python_core/__init__.py
python_core/config/__init__.py
python_core/config/constants.py
python_core/keywords/__init__.py
python_core/keywords/globkeyword.py
python_core/src/__init__.py
python_core/src/ts_execution.py
python_core/src/ts_generator.py
python_core/utils/__init__.py
python_core/utils/conftest.py
python_core/utils/fetch_data.py
python_core/utils/historical_report_gen.py
python_core/utils/keepReport.py
python_core/utils/objectData.py
python_core/utils/readData.py
python_core/utils/readingData.py
python_core/utils/xpath_generator.py
piedap-0.1.1.dist-info/METADATA
piedap-0.1.1.dist-info/WHEEL
piedap-0.1.1.dist-info/top_level.txt
piedap-0.1.1.dist-info/RECORD
