Metadata-Version: 2.1
Name: piedap
Version: 0.1.1
Summary: For generating TEST
Home-page: https://github.com/pgsecurity/seccuritytesting
Author: Anbusivan
Author-email: anbu.sivan@pionglobal.com
Classifier: Programming Language :: Python :: 3
Classifier: License :: OSI Approved :: MIT License
Classifier: Operating System :: OS Independent
Requires-Python: >=3.7
